refine/__init__.py
refine/main.py
refine/checkers/__init__.py
refine/checkers/base.py
refine/checkers/classical/__init__.py
refine/checkers/classical/boilerplate.py
refine/checkers/classical/contextual_sqli_audit.py
refine/checkers/classical/dependency_validation.py
refine/checkers/classical/hardcoded_secrets.py
refine/checkers/classical/package_check.py
refine/checkers/hybrid/__init__.py
refine/checkers/hybrid/base.py
refine/checkers/hybrid/boilerplate.py
refine/checkers/hybrid/sql_injection.py
refine/checkers/llm/__init__.py
refine/checkers/llm/base.py
refine/checkers/llm/comment_quality.py
refine/checkers/llm/dangerous_ai_logic.py
refine/checkers/llm/edge_cases.py
refine/checkers/llm/vibe_naming.py
refine/config/__init__.py
refine/config/loader.py
refine/config/schema.py
refine/core/__init__.py
refine/core/auditor.py
refine/core/chunker.py
refine/core/engine.py
refine/core/results.py
refine/providers/__init__.py
refine/providers/base.py
refine/providers/claude.py
refine/providers/google.py
refine/providers/openai.py
refine/ui/__init__.py
refine/ui/printer.py
refine_vibe_code-0.1.3.dist-info/METADATA
refine_vibe_code-0.1.3.dist-info/WHEEL
refine_vibe_code-0.1.3.dist-info/entry_points.txt
refine_vibe_code-0.1.3.dist-info/licenses/LICENSE
refine_vibe_code-0.1.3.dist-info/RECORD
