Metadata-Version: 2.4
Name: refine-vibe-code
Version: 0.1.3
Summary: CLI tool to identify AI-generated code and bad coding patterns
Project-URL: Homepage, https://github.com/CarlosMenke/refine-vibe-code
Project-URL: Repository, https://github.com/CarlosMenke/refine-vibe-code
Project-URL: Issues, https://github.com/CarlosMenke/refine-vibe-code/issues
Author-email: Carlos Menke <carlos.menke@rwth-aachen.de>
License-File: LICENSE
Keywords: ai-detection,cli,code-analysis,linting
Classifier: Development Status :: 3 - Alpha
Classifier: Intended Audience :: Developers
Classifier: License :: OSI Approved :: MIT License
Classifier: Programming Language :: Python :: 3
Classifier: Programming Language :: Python :: 3.12
Classifier: Topic :: Software Development :: Quality Assurance
Requires-Python: >=3.12
Requires-Dist: anthropic>=0.40.0
Requires-Dist: detect-secrets>=1.5.0
Requires-Dist: httpx>=0.25.0
Requires-Dist: openai>=1.0.0
Requires-Dist: pydantic>=2.0.0
Requires-Dist: pygments>=2.15.0
Requires-Dist: rich>=13.0.0
Requires-Dist: tomli-w>=1.0.0
Requires-Dist: tomli>=2.0.0; python_version < '3.11'
Requires-Dist: tomli>=2.3.0
Requires-Dist: typer[all]>=0.9.0
